robpitch/__init__.py
robpitch/base/__init__.py
robpitch/base/blocks/__init__.py
robpitch/base/blocks/common.py
robpitch/pitch/__init__.py
robpitch/pitch/base/__init__.py
robpitch/pitch/base/modules/__init__.py
robpitch/pitch/base/modules/pitch_predictor.py
robpitch/pitch/mel2pitch/__init__.py
robpitch/pitch/mel2pitch/inference.py
utils/__init__.py
utils/audio.py
utils/file.py
rob_pitch-0.1.2.dist-info/LICENSE
rob_pitch-0.1.2.dist-info/METADATA
rob_pitch-0.1.2.dist-info/WHEEL
rob_pitch-0.1.2.dist-info/top_level.txt
rob_pitch-0.1.2.dist-info/RECORD
