Metadata-Version: 2.1
Name: rob_pitch
Version: 0.1.2
Summary: Robust pitch prediction using PyTorch
Author: Xinsheng Wang, Mingqi Jiang
Author-email: w.xinshawn@gmail.com, mingqi.jiang@mobvoi.com
Classifier: Intended Audience :: Developers
Classifier: Intended Audience :: Science/Research
Classifier: Natural Language :: English
Classifier: Topic :: Artistic Software
Classifier: Topic :: Multimedia
Classifier: Topic :: Multimedia :: Sound/Audio
Classifier: Topic :: Software Development :: Libraries
Requires-Python: >=3.6
License-File: LICENSE
Requires-Dist: hydra-core==1.3.2
Requires-Dist: modelscope==1.18.0
Requires-Dist: numpy==1.24.3
Requires-Dist: omegaconf==2.3.0
Requires-Dist: setuptools==69.5.1
Requires-Dist: soundfile==0.12.1
Requires-Dist: soxr==0.3.7
Requires-Dist: torch==2.0.1
Requires-Dist: torchaudio==2.0.2
Requires-Dist: tqdm==4.66.5
